{"targets":[{"isStage":true,"name":"Stage","variables":{},"lists":{},"broadcasts":{},"blocks":{},"comments":{},"currentCostume":0,"costumes":[{"assetId":"c371efaccecb338cfbf99e3a526a8b42","name":"Racetrack","bitmapResolution":1,"md5ext":"c371efaccecb338cfbf99e3a526a8b42.svg","dataFormat":"svg","rotationCenterX":240,"rotationCenterY":180}],"sounds":[{"assetId":"83a9787d4cb6f3b7632b4ddfebf74367","name":"pop","dataFormat":"wav","format":"","rate":48000,"sampleCount":1123,"md5ext":"83a9787d4cb6f3b7632b4ddfebf74367.wav"}],"volume":100,"layerOrder":0,"tempo":60,"videoTransparency":50,"videoState":"off","textToSpeechLanguage":null},{"isStage":false,"name":"Bee","variables":{},"lists":{},"broadcasts":{},"blocks":{"fc85QpvL4#wMG(q)Ilv^":{"opcode":"event_whenflagclicked","next":"j12SR-([wVJ(ZJdK.D?e","parent":null,"inputs":{},"fields":{},"shadow":false,"topLevel":true,"x":15,"y":22},"j12SR-([wVJ(ZJdK.D?e":{"opcode":"motion_gotoxy","next":"{j/CmbtM)D~8Em2|?Y8F","parent":"fc85QpvL4#wMG(q)Ilv^","inputs":{"X":[1,[4,"-174"]],"Y":[1,[4,"-10"]]},"fields":{},"shadow":false,"topLevel":false},"{j/CmbtM)D~8Em2|?Y8F":{"opcode":"looks_switchcostumeto","next":null,"parent":"j12SR-([wVJ(ZJdK.D?e","inputs":{"COSTUME":[1,"N9|l}fXI(ht]`O0(dI5q"]},"fields":{},"shadow":false,"topLevel":false},"N9|l}fXI(ht]`O0(dI5q":{"opcode":"looks_costume","next":null,"parent":"{j/CmbtM)D~8Em2|?Y8F","inputs":{},"fields":{"COSTUME":["bumblebee1",null]},"shadow":true,"topLevel":false},";!zq59L/6IS[L@j=h|7p":{"opcode":"event_whenkeypressed","next":"5^g|?!vN4!,~#BS3Q{!I","parent":null,"inputs":{},"fields":{"KEY_OPTION":["down arrow",null]},"shadow":false,"topLevel":true,"x":13,"y":258},"/1Jorp:cXJukP1L]BxM^":{"opcode":"looks_switchcostumeto","next":"xoA;_5YlK[]mPc]tJ0_2","parent":"5^g|?!vN4!,~#BS3Q{!I","inputs":{"COSTUME":[1,"idfDxk|MMcp58}Y%8uPa"]},"fields":{},"shadow":false,"topLevel":false},"idfDxk|MMcp58}Y%8uPa":{"opcode":"looks_costume","next":null,"parent":"/1Jorp:cXJukP1L]BxM^","inputs":{},"fields":{"COSTUME":["bumblebee2",null]},"shadow":true,"topLevel":false},"iQu7zh?CcZP]@%F#}gt@":{"opcode":"looks_switchcostumeto","next":"B5`^]9Vgi9s20mXh*i2*","parent":"xoA;_5YlK[]mPc]tJ0_2","inputs":{"COSTUME":[1,"F1O#hzuiorW?quXrlS,w"]},"fields":{},"shadow":false,"topLevel":false},"F1O#hzuiorW?quXrlS,w":{"opcode":"looks_costume","next":null,"parent":"iQu7zh?CcZP]@%F#}gt@","inputs":{},"fields":{"COSTUME":["bumblebee3",null]},"shadow":true,"topLevel":false},"q;wOd@W5^BVe$jnCCl,~":{"opcode":"looks_switchcostumeto","next":"{Q!-0Fo=wdtCe?kT9]_d","parent":"B5`^]9Vgi9s20mXh*i2*","inputs":{"COSTUME":[1,"srwFhBjwsBA6}}/=U,Tk"]},"fields":{},"shadow":false,"topLevel":false},"srwFhBjwsBA6}}/=U,Tk":{"opcode":"looks_costume","next":null,"parent":"q;wOd@W5^BVe$jnCCl,~","inputs":{},"fields":{"COSTUME":["bumblebee4",null]},"shadow":true,"topLevel":false},"zpfj=B)7Z(Ivqq(,`ZFh":{"opcode":"looks_switchcostumeto","next":"SIdA?US#3a2?N6}L!8w,","parent":"{Q!-0Fo=wdtCe?kT9]_d","inputs":{"COSTUME":[1,"25jMS0Z_QY~ghKr^jGJo"]},"fields":{},"shadow":false,"topLevel":false},"25jMS0Z_QY~ghKr^jGJo":{"opcode":"looks_costume","next":null,"parent":"zpfj=B)7Z(Ivqq(,`ZFh","inputs":{},"fields":{"COSTUME":["bumblebee1",null]},"shadow":true,"topLevel":false},"5^g|?!vN4!,~#BS3Q{!I":{"opcode":"control_wait","next":"/1Jorp:cXJukP1L]BxM^","parent":";!zq59L/6IS[L@j=h|7p","inputs":{"DURATION":[1,[5,".2"]]},"fields":{},"shadow":false,"topLevel":false},"xoA;_5YlK[]mPc]tJ0_2":{"opcode":"control_wait","next":"iQu7zh?CcZP]@%F#}gt@","parent":"/1Jorp:cXJukP1L]BxM^","inputs":{"DURATION":[1,[5,"0.2"]]},"fields":{},"shadow":false,"topLevel":false},"B5`^]9Vgi9s20mXh*i2*":{"opcode":"control_wait","next":"q;wOd@W5^BVe$jnCCl,~","parent":"iQu7zh?CcZP]@%F#}gt@","inputs":{"DURATION":[1,[5,"0.2"]]},"fields":{},"shadow":false,"topLevel":false},"{Q!-0Fo=wdtCe?kT9]_d":{"opcode":"control_wait","next":"zpfj=B)7Z(Ivqq(,`ZFh","parent":"q;wOd@W5^BVe$jnCCl,~","inputs":{"DURATION":[1,[5,"0.2"]]},"fields":{},"shadow":false,"topLevel":false},"?IySlbEPZJ9`xn_*u+2z":{"opcode":"event_whenkeypressed","next":"TcI?1$l;)DZ4.sTZa^Y9","parent":null,"inputs":{},"fields":{"KEY_OPTION":["space",null]},"shadow":false,"topLevel":true,"x":13,"y":796},"TcI?1$l;)DZ4.sTZa^Y9":{"opcode":"control_repeat","next":null,"parent":"?IySlbEPZJ9`xn_*u+2z","inputs":{"TIMES":[1,[6,"36"]],"SUBSTACK":[2,"NkWnDoFsU]DOa)CFnSA%"]},"fields":{},"shadow":false,"topLevel":false},"NkWnDoFsU]DOa)CFnSA%":{"opcode":"control_wait","next":"]U5Fy-F_k,i9gCZ2*q/#","parent":"TcI?1$l;)DZ4.sTZa^Y9","inputs":{"DURATION":[1,[5,"0.1"]]},"fields":{},"shadow":false,"topLevel":false},"]U5Fy-F_k,i9gCZ2*q/#":{"opcode":"looks_nextcostume","next":"nS$):8T/z7Au=nP9,=E)","parent":"NkWnDoFsU]DOa)CFnSA%","inputs":{},"fields":{},"shadow":false,"topLevel":false},"nS$):8T/z7Au=nP9,=E)":{"opcode":"motion_movesteps","next":null,"parent":"]U5Fy-F_k,i9gCZ2*q/#","inputs":{"STEPS":[1,[4,"10"]]},"fields":{},"shadow":false,"topLevel":false},"SIdA?US#3a2?N6}L!8w,":{"opcode":"control_wait","next":null,"parent":"zpfj=B)7Z(Ivqq(,`ZFh","inputs":{"DURATION":[1,[5,"0.2"]]},"fields":{},"shadow":false,"topLevel":false}},"comments":{"XOQe6}q:GFK#7^bM?kc=":{"blockId":null,"x":558,"y":319,"width":232,"height":160,"minimized":false,"text":"Build 2 scripts here."},"97.1JM1@^7hmcSacpJVG":{"blockId":null,"x":557,"y":483,"width":241,"height":299,"minimized":false,"text":"One will have the Bee flap its wings, while it stays in one location, when the down arrow key is pressed. Look at the script on the Monkey sprite."},"-Kx{+[sI?:F*!fKOl0^)":{"blockId":null,"x":560,"y":803,"width":241,"height":297,"minimized":false,"text":"The other will have the Bee flap its wings and move across the stage to the finish line when the space key is pressed. Look at the script on the Snake sprite."}},"currentCostume":0,"costumes":[{"assetId":"138337122861e6f93ade94301d21d5e0","name":"bumblebee1","bitmapResolution":1,"md5ext":"138337122861e6f93ade94301d21d5e0.svg","dataFormat":"svg","rotationCenterX":169,"rotationCenterY":90},{"assetId":"f18c726c54a429d4b059fd1b95b66b1b","name":"bumblebee2","bitmapResolution":1,"md5ext":"f18c726c54a429d4b059fd1b95b66b1b.svg","dataFormat":"svg","rotationCenterX":181,"rotationCenterY":72},{"assetId":"e575ce0d29f553050cea2507e476ef1c","name":"bumblebee3","bitmapResolution":1,"md5ext":"e575ce0d29f553050cea2507e476ef1c.svg","dataFormat":"svg","rotationCenterX":181,"rotationCenterY":88},{"assetId":"631545e48675960943fbe32bfdde2dce","name":"bumblebee4","bitmapResolution":1,"md5ext":"631545e48675960943fbe32bfdde2dce.svg","dataFormat":"svg","rotationCenterX":232,"rotationCenterY":72}],"sounds":[{"assetId":"83a9787d4cb6f3b7632b4ddfebf74367","name":"pop","dataFormat":"wav","format":"","rate":48000,"sampleCount":1123,"md5ext":"83a9787d4cb6f3b7632b4ddfebf74367.wav"}],"volume":100,"layerOrder":3,"visible":true,"x":137.76914536239795,"y":169.99999999999997,"size":45.000000000000014,"direction":60,"draggable":false,"rotationStyle":"left-right"},{"isStage":false,"name":"Snake","variables":{},"lists":{},"broadcasts":{},"blocks":{"yGH,UrvXziXK.z8Ty;H7":{"opcode":"event_whenflagclicked","next":"4g|w7IDzoIxI^4IRTUUD","parent":null,"inputs":{},"fields":{},"shadow":false,"topLevel":true,"x":15,"y":22},"4g|w7IDzoIxI^4IRTUUD":{"opcode":"motion_gotoxy","next":":dDP|r-RRR*eiZNs3OVz","parent":"yGH,UrvXziXK.z8Ty;H7","inputs":{"X":[1,[4,-211]],"Y":[1,[4,-133]]},"fields":{},"shadow":false,"topLevel":false},":dDP|r-RRR*eiZNs3OVz":{"opcode":"looks_switchcostumeto","next":";My-hU,yW#=0bs+MM/X/","parent":"4g|w7IDzoIxI^4IRTUUD","inputs":{"COSTUME":[1,"mn?4FdW_R[[Aqo=B2TuU"]},"fields":{},"shadow":false,"topLevel":false},"mn?4FdW_R[[Aqo=B2TuU":{"opcode":"looks_costume","next":null,"parent":":dDP|r-RRR*eiZNs3OVz","inputs":{},"fields":{"COSTUME":["snake1"]},"shadow":true,"topLevel":false},";My-hU,yW#=0bs+MM/X/":{"opcode":"looks_sayforsecs","next":null,"parent":":dDP|r-RRR*eiZNs3OVz","inputs":{"MESSAGE":[1,[10,"Hsss..."]],"SECS":[1,[4,2]]},"fields":{},"shadow":false,"topLevel":false},"Jp9o|[aicASbQl/9}3wc":{"opcode":"event_whenkeypressed","next":"nyU=v8FOZ_K!r%Q+/S}a","parent":null,"inputs":{},"fields":{"KEY_OPTION":["down arrow"]},"shadow":false,"topLevel":true,"x":22,"y":360},"nyU=v8FOZ_K!r%Q+/S}a":{"opcode":"control_wait","next":"Sj)8w!sRAL~C{zFA[r4g","parent":"Jp9o|[aicASbQl/9}3wc","inputs":{"DURATION":[1,[5,0.2]]},"fields":{},"shadow":false,"topLevel":false},"Sj)8w!sRAL~C{zFA[r4g":{"opcode":"looks_switchcostumeto","next":"}hmm%A:93{ZxHL3wurK-","parent":"nyU=v8FOZ_K!r%Q+/S}a","inputs":{"COSTUME":[1,"fVT3I=wwyWoDMP[67YY-"]},"fields":{},"shadow":false,"topLevel":false},"fVT3I=wwyWoDMP[67YY-":{"opcode":"looks_costume","next":null,"parent":"Sj)8w!sRAL~C{zFA[r4g","inputs":{},"fields":{"COSTUME":["snake2"]},"shadow":true,"topLevel":false},"}hmm%A:93{ZxHL3wurK-":{"opcode":"control_wait","next":"bkdWT:t`zQJ^#!rd+@xz","parent":"Sj)8w!sRAL~C{zFA[r4g","inputs":{"DURATION":[1,[5,0.2]]},"fields":{},"shadow":false,"topLevel":false},"bkdWT:t`zQJ^#!rd+@xz":{"opcode":"looks_switchcostumeto","next":"*2dl~K.b/k*CS|ha-*,D","parent":"}hmm%A:93{ZxHL3wurK-","inputs":{"COSTUME":[1,"+^K#?RhIZ(@b#K40H%c#"]},"fields":{},"shadow":false,"topLevel":false},"+^K#?RhIZ(@b#K40H%c#":{"opcode":"looks_costume","next":null,"parent":"bkdWT:t`zQJ^#!rd+@xz","inputs":{},"fields":{"COSTUME":["snake3"]},"shadow":true,"topLevel":false},"*2dl~K.b/k*CS|ha-*,D":{"opcode":"control_wait","next":"/:L7x@:tDU.T5q]In-HU","parent":"bkdWT:t`zQJ^#!rd+@xz","inputs":{"DURATION":[1,[5,0.2]]},"fields":{},"shadow":false,"topLevel":false},"/:L7x@:tDU.T5q]In-HU":{"opcode":"looks_switchcostumeto","next":"eK~/[q*j4wNm0*z{=Fou","parent":"*2dl~K.b/k*CS|ha-*,D","inputs":{"COSTUME":[1,"lUZlBaM`kmatS?;r%JH6"]},"fields":{},"shadow":false,"topLevel":false},"lUZlBaM`kmatS?;r%JH6":{"opcode":"looks_costume","next":null,"parent":"/:L7x@:tDU.T5q]In-HU","inputs":{},"fields":{"COSTUME":["snake4"]},"shadow":true,"topLevel":false},"eK~/[q*j4wNm0*z{=Fou":{"opcode":"control_wait","next":null,"parent":"/:L7x@:tDU.T5q]In-HU","inputs":{"DURATION":[1,[5,0.2]]},"fields":{},"shadow":false,"topLevel":false},"#52qF?_5b.TFbglz`^gH":{"opcode":"event_whenkeypressed","next":".hoM4KH@n2DM{(,/:l@8","parent":null,"inputs":{},"fields":{"KEY_OPTION":["space"]},"shadow":false,"topLevel":true,"x":24,"y":836},".hoM4KH@n2DM{(,/:l@8":{"opcode":"control_repeat","next":null,"parent":"#52qF?_5b.TFbglz`^gH","inputs":{"TIMES":[1,[6,36]],"SUBSTACK":[2,"YXx/R7dcVk2C*W|Rck!="]},"fields":{},"shadow":false,"topLevel":false},"YXx/R7dcVk2C*W|Rck!=":{"opcode":"control_wait","next":"ef70#YMM`Deas`yH2a/0","parent":".hoM4KH@n2DM{(,/:l@8","inputs":{"DURATION":[1,[5,"0.3"]]},"fields":{},"shadow":false,"topLevel":false},"ef70#YMM`Deas`yH2a/0":{"opcode":"looks_nextcostume","next":"o[|#Og=b8%#.w{9%Z+}1","parent":"YXx/R7dcVk2C*W|Rck!=","inputs":{},"fields":{},"shadow":false,"topLevel":false},"o[|#Og=b8%#.w{9%Z+}1":{"opcode":"motion_movesteps","next":null,"parent":"ef70#YMM`Deas`yH2a/0","inputs":{"STEPS":[1,[4,10]]},"fields":{},"shadow":false,"topLevel":false}},"comments":{},"currentCostume":0,"costumes":[{"assetId":"92cf0da9269330eca76425af0ff15260","name":"snake1","bitmapResolution":1,"md5ext":"92cf0da9269330eca76425af0ff15260.svg","dataFormat":"svg","rotationCenterX":117,"rotationCenterY":50},{"assetId":"c87d337d41d197b4f5919cc66156097f","name":"snake2","bitmapResolution":1,"md5ext":"c87d337d41d197b4f5919cc66156097f.svg","dataFormat":"svg","rotationCenterX":146,"rotationCenterY":58},{"assetId":"2a58d679de6c23e68a35928ca96d5599","name":"snake3","bitmapResolution":1,"md5ext":"2a58d679de6c23e68a35928ca96d5599.svg","dataFormat":"svg","rotationCenterX":171,"rotationCenterY":61},{"assetId":"651f2115e2c171d2f445145c6445b9d2","name":"snake4","bitmapResolution":1,"md5ext":"651f2115e2c171d2f445145c6445b9d2.svg","dataFormat":"svg","rotationCenterX":156,"rotationCenterY":57}],"sounds":[{"assetId":"83a9787d4cb6f3b7632b4ddfebf74367","name":"pop","dataFormat":"wav","format":"","rate":48000,"sampleCount":1123,"md5ext":"83a9787d4cb6f3b7632b4ddfebf74367.wav"}],"volume":100,"layerOrder":1,"visible":true,"x":149,"y":-133,"size":85,"direction":90,"draggable":false,"rotationStyle":"left-right"},{"isStage":false,"name":"Monkey ","variables":{},"lists":{},"broadcasts":{},"blocks":{"zzV@v#QzQ.Gk-C1#D/kb":{"opcode":"event_whenflagclicked","next":"Vj^`|#WcsSmxiUCU@Up(","parent":null,"inputs":{},"fields":{},"shadow":false,"topLevel":true,"x":37,"y":33},"Vj^`|#WcsSmxiUCU@Up(":{"opcode":"looks_switchcostumeto","next":"-%,%C(kJ||L(22H/So+^","parent":"zzV@v#QzQ.Gk-C1#D/kb","inputs":{"COSTUME":[1,"!pkaM9LVHFv0{V@_@sIT"]},"fields":{},"shadow":false,"topLevel":false},"!pkaM9LVHFv0{V@_@sIT":{"opcode":"looks_costume","next":null,"parent":"Vj^`|#WcsSmxiUCU@Up(","inputs":{},"fields":{"COSTUME":["monkey top right"]},"shadow":true,"topLevel":false},"-%,%C(kJ||L(22H/So+^":{"opcode":"motion_gotoxy","next":"K6(W^rSXb=es:2{r(Q5P","parent":"Vj^`|#WcsSmxiUCU@Up(","inputs":{"X":[1,[4,-12]],"Y":[1,[4,83]]},"fields":{},"shadow":false,"topLevel":false},"K6(W^rSXb=es:2{r(Q5P":{"opcode":"looks_sayforsecs","next":"SOn260TQO|~Zbn98yyIL","parent":"-%,%C(kJ||L(22H/So+^","inputs":{"MESSAGE":[1,[10,"We're having a race today!"]],"SECS":[1,[4,2]]},"fields":{},"shadow":false,"topLevel":false},"SOn260TQO|~Zbn98yyIL":{"opcode":"looks_sayforsecs","next":"lp_[41I4xisQc4a)IT8O","parent":"K6(W^rSXb=es:2{r(Q5P","inputs":{"MESSAGE":[1,[10,"Press the down arrow to watch me wave my flag."]],"SECS":[1,[4,4]]},"fields":{},"shadow":false,"topLevel":false},"lp_[41I4xisQc4a)IT8O":{"opcode":"looks_sayforsecs","next":null,"parent":"SOn260TQO|~Zbn98yyIL","inputs":{"MESSAGE":[1,[10,"Then, press the spacebar to start the race!"]],"SECS":[1,[4,3]]},"fields":{},"shadow":false,"topLevel":false},"WC7digI7B1CAaQk|f^.3":{"opcode":"event_whenkeypressed","next":"-M|@[BB]j=nvE:HvB0tu","parent":null,"inputs":{},"fields":{"KEY_OPTION":["down arrow"]},"shadow":false,"topLevel":true,"x":40,"y":413},"-M|@[BB]j=nvE:HvB0tu":{"opcode":"control_wait","next":"/g9%J{1RTjWBBPcmXEkc","parent":"WC7digI7B1CAaQk|f^.3","inputs":{"DURATION":[1,[5,0.2]]},"fields":{},"shadow":false,"topLevel":false},"/g9%J{1RTjWBBPcmXEkc":{"opcode":"looks_switchcostumeto","next":"L314-fLs@!JQ##0htl-i","parent":"-M|@[BB]j=nvE:HvB0tu","inputs":{"COSTUME":[1,"I-D1FrrC0_z:zn9H6njt"]},"fields":{},"shadow":false,"topLevel":false},"I-D1FrrC0_z:zn9H6njt":{"opcode":"looks_costume","next":null,"parent":"/g9%J{1RTjWBBPcmXEkc","inputs":{},"fields":{"COSTUME":["monkey bottom right"]},"shadow":true,"topLevel":false},"L314-fLs@!JQ##0htl-i":{"opcode":"control_wait","next":"7uf4?2ec3ra6=#)hmJkX","parent":"/g9%J{1RTjWBBPcmXEkc","inputs":{"DURATION":[1,[5,0.2]]},"fields":{},"shadow":false,"topLevel":false},"7uf4?2ec3ra6=#)hmJkX":{"opcode":"looks_switchcostumeto","next":"[)O0w?!u|[y,,ZDmusXw","parent":"L314-fLs@!JQ##0htl-i","inputs":{"COSTUME":[1,"pw^J,0W!00,4LHlmUa!*"]},"fields":{},"shadow":false,"topLevel":false},"pw^J,0W!00,4LHlmUa!*":{"opcode":"looks_costume","next":null,"parent":"7uf4?2ec3ra6=#)hmJkX","inputs":{},"fields":{"COSTUME":["monkey bottom left"]},"shadow":true,"topLevel":false},"[)O0w?!u|[y,,ZDmusXw":{"opcode":"control_wait","next":"L.%SPZb/KbpX!LGr{oXn","parent":"7uf4?2ec3ra6=#)hmJkX","inputs":{"DURATION":[1,[5,0.2]]},"fields":{},"shadow":false,"topLevel":false},"L.%SPZb/KbpX!LGr{oXn":{"opcode":"looks_switchcostumeto","next":"NscIa,!N:Tsu1~ee/.!Y","parent":"[)O0w?!u|[y,,ZDmusXw","inputs":{"COSTUME":[1,"htQG@k(@81OG97d`4UX["]},"fields":{},"shadow":false,"topLevel":false},"htQG@k(@81OG97d`4UX[":{"opcode":"looks_costume","next":null,"parent":"L.%SPZb/KbpX!LGr{oXn","inputs":{},"fields":{"COSTUME":["monkey top left"]},"shadow":true,"topLevel":false},"NscIa,!N:Tsu1~ee/.!Y":{"opcode":"control_wait","next":"A.hz[)(.,nt}MEtPS}3M","parent":"L.%SPZb/KbpX!LGr{oXn","inputs":{"DURATION":[1,[5,0.2]]},"fields":{},"shadow":false,"topLevel":false},"A.hz[)(.,nt}MEtPS}3M":{"opcode":"looks_switchcostumeto","next":null,"parent":"NscIa,!N:Tsu1~ee/.!Y","inputs":{"COSTUME":[1,"k3eU6H;7o#SXA]M~Q((0"]},"fields":{},"shadow":false,"topLevel":false},"k3eU6H;7o#SXA]M~Q((0":{"opcode":"looks_costume","next":null,"parent":"A.hz[)(.,nt}MEtPS}3M","inputs":{},"fields":{"COSTUME":["monkey top right"]},"shadow":true,"topLevel":false},"f?}BHK:%sQJ0ETS5~I3q":{"opcode":"event_whenkeypressed","next":",noLf*IQsT,0SbI_^g)9","parent":null,"inputs":{},"fields":{"KEY_OPTION":["space"]},"shadow":false,"topLevel":true,"x":44,"y":936},",noLf*IQsT,0SbI_^g)9":{"opcode":"looks_sayforsecs","next":"YuI`dknm2Mn?ph*=7A-T","parent":"f?}BHK:%sQJ0ETS5~I3q","inputs":{"MESSAGE":[1,[10,"Go!"]],"SECS":[1,[4,2]]},"fields":{},"shadow":false,"topLevel":false},"YuI`dknm2Mn?ph*=7A-T":{"opcode":"control_repeat","next":"iHJ{v7lQ:ZYhJ.XBCv:Z","parent":",noLf*IQsT,0SbI_^g)9","inputs":{"TIMES":[1,[6,36]],"SUBSTACK":[2,"A+bk*Q@y^)l`^XhyVMXp"]},"fields":{},"shadow":false,"topLevel":false},"A+bk*Q@y^)l`^XhyVMXp":{"opcode":"control_wait","next":"Ss[{LA/j*:+C_ZoCGVr0","parent":"YuI`dknm2Mn?ph*=7A-T","inputs":{"DURATION":[1,[5,0.2]]},"fields":{},"shadow":false,"topLevel":false},"Ss[{LA/j*:+C_ZoCGVr0":{"opcode":"looks_nextcostume","next":null,"parent":"A+bk*Q@y^)l`^XhyVMXp","inputs":{},"fields":{},"shadow":false,"topLevel":false},"iHJ{v7lQ:ZYhJ.XBCv:Z":{"opcode":"looks_sayforsecs","next":null,"parent":"YuI`dknm2Mn?ph*=7A-T","inputs":{"MESSAGE":[1,[10,"Yay!!!"]],"SECS":[1,[4,2]]},"fields":{},"shadow":false,"topLevel":false}},"comments":{},"currentCostume":0,"costumes":[{"assetId":"107d47ecc7377b5b3192d8ba832ef2ef","name":"monkey top right","bitmapResolution":1,"md5ext":"107d47ecc7377b5b3192d8ba832ef2ef.svg","dataFormat":"svg","rotationCenterX":139,"rotationCenterY":130},{"assetId":"c759fe2dfc5a76191f8b70bbc852337c","name":"monkey bottom right","bitmapResolution":2,"md5ext":"c759fe2dfc5a76191f8b70bbc852337c.png","dataFormat":"png","rotationCenterX":285,"rotationCenterY":248},{"assetId":"3d705748231f2e1351f78397b486a472","name":"monkey bottom left","bitmapResolution":2,"md5ext":"3d705748231f2e1351f78397b486a472.png","dataFormat":"png","rotationCenterX":275,"rotationCenterY":255},{"assetId":"1fc6c2c6386367da5a2e94a29310dd4a","name":"monkey top left","bitmapResolution":2,"md5ext":"1fc6c2c6386367da5a2e94a29310dd4a.png","dataFormat":"png","rotationCenterX":376,"rotationCenterY":276}],"sounds":[{"assetId":"83a9787d4cb6f3b7632b4ddfebf74367","name":"pop","dataFormat":"wav","format":"","rate":48000,"sampleCount":1123,"md5ext":"83a9787d4cb6f3b7632b4ddfebf74367.wav"}],"volume":100,"layerOrder":4,"visible":true,"x":-12,"y":83,"size":35.000000000000014,"direction":90,"draggable":false,"rotationStyle":"left-right"},{"isStage":false,"name":"Kangaroo","variables":{},"lists":{},"broadcasts":{},"blocks":{"!q7;~cRb9|B1{,4kVU(u":{"opcode":"event_whenflagclicked","next":"f~IMr=^MzUj6~!Gz2Y/z","parent":null,"inputs":{},"fields":{},"shadow":false,"topLevel":true,"x":22,"y":61},"f~IMr=^MzUj6~!Gz2Y/z":{"opcode":"motion_gotoxy","next":"hZs=Suh+=B9e70r:|cV%","parent":"!q7;~cRb9|B1{,4kVU(u","inputs":{"X":[1,[4,-205]],"Y":[1,[4,72]]},"fields":{},"shadow":false,"topLevel":false},"hZs=Suh+=B9e70r:|cV%":{"opcode":"looks_switchcostumeto","next":null,"parent":"f~IMr=^MzUj6~!Gz2Y/z","inputs":{"COSTUME":[1,"SHP)v[O{6RD=Nf*FkYPP"]},"fields":{},"shadow":false,"topLevel":false},"SHP)v[O{6RD=Nf*FkYPP":{"opcode":"looks_costume","next":null,"parent":"hZs=Suh+=B9e70r:|cV%","inputs":{},"fields":{"COSTUME":["kangaroo crouching"]},"shadow":true,"topLevel":false}},"comments":{},"currentCostume":0,"costumes":[{"assetId":"ad0c213802ff8ca0828f0bf9d4f98170","name":"kangaroo crouching","bitmapResolution":1,"md5ext":"ad0c213802ff8ca0828f0bf9d4f98170.svg","dataFormat":"svg","rotationCenterX":83,"rotationCenterY":100},{"assetId":"b302b866bc09cc452e4afd9bf02b3889","name":"kangaroo half jump","bitmapResolution":1,"md5ext":"b302b866bc09cc452e4afd9bf02b3889.svg","dataFormat":"svg","rotationCenterX":83,"rotationCenterY":113},{"assetId":"cd7e0f52e8a6925d5070eade048d554e","name":"kangaroo jump","bitmapResolution":1,"md5ext":"cd7e0f52e8a6925d5070eade048d554e.svg","dataFormat":"svg","rotationCenterX":61,"rotationCenterY":92},{"assetId":"b302b866bc09cc452e4afd9bf02b3889","name":"kangaroo half jump2","bitmapResolution":1,"md5ext":"b302b866bc09cc452e4afd9bf02b3889.svg","dataFormat":"svg","rotationCenterX":83,"rotationCenterY":113}],"sounds":[{"assetId":"83a9787d4cb6f3b7632b4ddfebf74367","name":"pop","dataFormat":"wav","format":"","rate":48000,"sampleCount":1123,"md5ext":"83a9787d4cb6f3b7632b4ddfebf74367.wav"}],"volume":100,"layerOrder":2,"visible":false,"x":-205,"y":72,"size":60,"direction":90,"draggable":false,"rotationStyle":"left-right"}],"monitors":[],"extensions":[],"meta":{"semver":"3.0.0","vm":"0.2.0-prerelease.20190321151527","agent":"Mozilla/5.0 (X11; CrOS aarch64 11647.104.0) AppleWebKit/537.36 (KHTML, like Gecko) Chrome/73.0.3683.88 Safari/537.36"}}