{"targets":[{"isStage":true,"name":"Stage","variables":{"+Y:KzQ2YKvPQBK#]yay8-broadcast message-":["broadcast message","stop"],"+Y:KzQ2YKvPQBK#]yay8-add to band-":["add to band","sax"]},"lists":{},"broadcasts":{"broadcastMsgId-navajo":"navajo","TL?SB+/IyvN1M{jjF7`[":"Mali Djembe"},"blocks":{},"comments":{},"currentCostume":1,"costumes":[{"assetId":"531a943ae6e8b7d9ea34641277495d6e","name":"Navajo and Mali Landscape","bitmapResolution":1,"md5ext":"531a943ae6e8b7d9ea34641277495d6e.svg","dataFormat":"svg","rotationCenterX":240,"rotationCenterY":180},{"assetId":"522f316c6ff891ad25530ec105e654a4","name":"stage1","bitmapResolution":1,"md5ext":"522f316c6ff891ad25530ec105e654a4.svg","dataFormat":"svg","rotationCenterX":255.55649543937596,"rotationCenterY":218.64306498543237},{"assetId":"6aa914e018b22b80afeb554e00605371","name":"stage2","bitmapResolution":2,"md5ext":"6aa914e018b22b80afeb554e00605371.png","dataFormat":"png","rotationCenterX":480,"rotationCenterY":360}],"sounds":[{"assetId":"83a9787d4cb6f3b7632b4ddfebf74367","name":"pop","dataFormat":"wav","format":"","rate":48000,"sampleCount":1123,"md5ext":"83a9787d4cb6f3b7632b4ddfebf74367.wav"}],"volume":100,"layerOrder":0,"tempo":40,"videoTransparency":50,"videoState":"off","textToSpeechLanguage":null},{"isStage":false,"name":"Navajo Flute","variables":{},"lists":{},"broadcasts":{},"blocks":{"$XZ(mp}CL7*U6%2Ucr`|":{"opcode":"event_whenflagclicked","next":"~)^dCW.RNgKV3VirGW1N","parent":null,"inputs":{},"fields":{},"shadow":false,"topLevel":true,"x":712,"y":67},"~)^dCW.RNgKV3VirGW1N":{"opcode":"event_broadcast","next":"Pf7n=)Fa#eB~KUx(OJ[F","parent":"$XZ(mp}CL7*U6%2Ucr`|","inputs":{"BROADCAST_INPUT":[1,[11,"navajo","broadcastMsgId-navajo"]]},"fields":{},"shadow":false,"topLevel":false},"Pf7n=)Fa#eB~KUx(OJ[F":{"opcode":"sound_play","next":null,"parent":"~)^dCW.RNgKV3VirGW1N","inputs":{"SOUND_MENU":[1,"PEprv801o-24Maez0V%)"]},"fields":{},"shadow":false,"topLevel":false},"PEprv801o-24Maez0V%)":{"opcode":"sound_sounds_menu","next":null,"parent":"Pf7n=)Fa#eB~KUx(OJ[F","inputs":{},"fields":{"SOUND_MENU":["Navajo Flute",null]},"shadow":true,"topLevel":false}},"comments":{},"currentCostume":0,"costumes":[{"assetId":"406f4565506a15d3831849228eac5c51","name":"nativeAmericanFlute","bitmapResolution":2,"md5ext":"406f4565506a15d3831849228eac5c51.png","dataFormat":"png","rotationCenterX":-37,"rotationCenterY":149}],"sounds":[{"assetId":"0f0f24fc2b4e03758aa90109b7e3e305","name":"Navajo Flute","dataFormat":"wav","format":"","rate":48000,"sampleCount":525792,"md5ext":"0f0f24fc2b4e03758aa90109b7e3e305.wav"}],"volume":100,"layerOrder":4,"visible":true,"x":-225,"y":-160,"size":100,"direction":90,"draggable":false,"rotationStyle":"all around"},{"isStage":false,"name":"Mali Djembe","variables":{},"lists":{},"broadcasts":{},"blocks":{"t0J}tSjOm4_uB-*vHfuD":{"opcode":"event_broadcast","next":"QXwzr#.?Wl?l5A{@6DJ0","parent":"[zAt)V%`lbg|:?p:c;(7","inputs":{"BROADCAST_INPUT":[1,[11,"Mali Djembe","TL?SB+/IyvN1M{jjF7`["]]},"fields":{},"shadow":false,"topLevel":false},"QXwzr#.?Wl?l5A{@6DJ0":{"opcode":"sound_play","next":null,"parent":"t0J}tSjOm4_uB-*vHfuD","inputs":{"SOUND_MENU":[1,"t`k.ikw)e)4S@NRt0-Cu"]},"fields":{},"shadow":false,"topLevel":false},"t`k.ikw)e)4S@NRt0-Cu":{"opcode":"sound_sounds_menu","next":null,"parent":"QXwzr#.?Wl?l5A{@6DJ0","inputs":{},"fields":{"SOUND_MENU":["djembe",null]},"shadow":true,"topLevel":false},"[zAt)V%`lbg|:?p:c;(7":{"opcode":"event_whenflagclicked","next":"t0J}tSjOm4_uB-*vHfuD","parent":null,"inputs":{},"fields":{},"shadow":false,"topLevel":true,"x":447,"y":82}},"comments":{},"currentCostume":0,"costumes":[{"assetId":"f8eec7b1e119c43c386362a2c8ed039f","name":"AfricanDrum","bitmapResolution":2,"md5ext":"f8eec7b1e119c43c386362a2c8ed039f.png","dataFormat":"png","rotationCenterX":-21,"rotationCenterY":152}],"sounds":[{"assetId":"b6e43d1f6ac8d8f082c171f20c2612cb","name":"djembe","dataFormat":"wav","format":"adpcm","rate":22050,"sampleCount":176785,"md5ext":"b6e43d1f6ac8d8f082c171f20c2612cb.wav"}],"volume":100,"layerOrder":6,"visible":true,"x":14.000000000000028,"y":-152.00000000000003,"size":100,"direction":90,"draggable":false,"rotationStyle":"all around"},{"isStage":false,"name":"Navajo child","variables":{},"lists":{},"broadcasts":{},"blocks":{"Ld;w(N?A?wgQwJts[*Bk":{"opcode":"event_whenbroadcastreceived","next":"62;F}[MD!}NC8FhQ.I7f","parent":null,"inputs":{},"fields":{"BROADCAST_OPTION":["navajo","broadcastMsgId-navajo"]},"shadow":false,"topLevel":true,"x":615,"y":147},"62;F}[MD!}NC8FhQ.I7f":{"opcode":"control_repeat","next":null,"parent":"Ld;w(N?A?wgQwJts[*Bk","inputs":{"TIMES":[1,[6,"22"]],"SUBSTACK":[2,"Ya9kmlG7_T`4@[UbrtbT"]},"fields":{},"shadow":false,"topLevel":false},"Ya9kmlG7_T`4@[UbrtbT":{"opcode":"looks_nextcostume","next":"TYR83e_lrI1tvBqH}s#8","parent":"62;F}[MD!}NC8FhQ.I7f","inputs":{},"fields":{},"shadow":false,"topLevel":false},"TYR83e_lrI1tvBqH}s#8":{"opcode":"control_wait","next":null,"parent":"Ya9kmlG7_T`4@[UbrtbT","inputs":{"DURATION":[1,[5,"0.5"]]},"fields":{},"shadow":false,"topLevel":false}},"comments":{},"currentCostume":3,"costumes":[{"assetId":"a95bb303fd6b01e590bb737f2751fe81","name":"center","bitmapResolution":1,"md5ext":"a95bb303fd6b01e590bb737f2751fe81.svg","dataFormat":"svg","rotationCenterX":37.5,"rotationCenterY":88.94999999999999},{"assetId":"a46b5c59be6769d403053343b211b06f","name":"left","bitmapResolution":1,"md5ext":"a46b5c59be6769d403053343b211b06f.svg","dataFormat":"svg","rotationCenterX":37.599999999999994,"rotationCenterY":87.1},{"assetId":"a2796f739d629b41d995d211fd85ffd7","name":"center2","bitmapResolution":1,"md5ext":"a2796f739d629b41d995d211fd85ffd7.svg","dataFormat":"svg","rotationCenterX":41.59567000000001,"rotationCenterY":87.55000000000001},{"assetId":"102b68af4dc970daeff07cd3550bfbf7","name":"right","bitmapResolution":1,"md5ext":"102b68af4dc970daeff07cd3550bfbf7.svg","dataFormat":"svg","rotationCenterX":37.44999999999999,"rotationCenterY":88.94999999999999}],"sounds":[{"assetId":"83a9787d4cb6f3b7632b4ddfebf74367","name":"pop","dataFormat":"wav","format":"","rate":48000,"sampleCount":1123,"md5ext":"83a9787d4cb6f3b7632b4ddfebf74367.wav"}],"volume":100,"layerOrder":2,"visible":true,"x":-47.999999999999986,"y":-17.000000000000007,"size":100,"direction":90,"draggable":false,"rotationStyle":"all around"},{"isStage":false,"name":"Navajo child2","variables":{},"lists":{},"broadcasts":{},"blocks":{"Ld;w(N?A?wgQwJts[*Bk":{"opcode":"event_whenbroadcastreceived","next":"62;F}[MD!}NC8FhQ.I7f","parent":null,"inputs":{},"fields":{"BROADCAST_OPTION":["navajo","broadcastMsgId-navajo"]},"shadow":false,"topLevel":true,"x":615,"y":147},"62;F}[MD!}NC8FhQ.I7f":{"opcode":"control_repeat","next":null,"parent":"Ld;w(N?A?wgQwJts[*Bk","inputs":{"TIMES":[1,[6,"22"]],"SUBSTACK":[2,"Ya9kmlG7_T`4@[UbrtbT"]},"fields":{},"shadow":false,"topLevel":false},"Ya9kmlG7_T`4@[UbrtbT":{"opcode":"looks_nextcostume","next":"TYR83e_lrI1tvBqH}s#8","parent":"62;F}[MD!}NC8FhQ.I7f","inputs":{},"fields":{},"shadow":false,"topLevel":false},"TYR83e_lrI1tvBqH}s#8":{"opcode":"control_wait","next":null,"parent":"Ya9kmlG7_T`4@[UbrtbT","inputs":{"DURATION":[1,[5,"0.5"]]},"fields":{},"shadow":false,"topLevel":false}},"comments":{},"currentCostume":3,"costumes":[{"assetId":"c6b067aa617f2bcca358849ed352a0bf","name":"center","bitmapResolution":1,"md5ext":"c6b067aa617f2bcca358849ed352a0bf.svg","dataFormat":"svg","rotationCenterX":37.5,"rotationCenterY":88.94999999999999},{"assetId":"dc70fbf3e8d18057086c539dc1fd68df","name":"left","bitmapResolution":1,"md5ext":"dc70fbf3e8d18057086c539dc1fd68df.svg","dataFormat":"svg","rotationCenterX":37.599999999999994,"rotationCenterY":87.1},{"assetId":"af97a90d0efa1612c688717cc50e81b4","name":"center2","bitmapResolution":1,"md5ext":"af97a90d0efa1612c688717cc50e81b4.svg","dataFormat":"svg","rotationCenterX":36.849999999999994,"rotationCenterY":87.55000000000001},{"assetId":"2659929551c0e22dc30c0b88c85c5990","name":"right","bitmapResolution":1,"md5ext":"2659929551c0e22dc30c0b88c85c5990.svg","dataFormat":"svg","rotationCenterX":37.44999999999999,"rotationCenterY":88.94999999999999}],"sounds":[{"assetId":"83a9787d4cb6f3b7632b4ddfebf74367","name":"pop","dataFormat":"wav","format":"","rate":48000,"sampleCount":1123,"md5ext":"83a9787d4cb6f3b7632b4ddfebf74367.wav"}],"volume":100,"layerOrder":5,"visible":true,"x":-168,"y":-21.000000000000014,"size":100,"direction":90,"draggable":false,"rotationStyle":"all around"},{"isStage":false,"name":"Navajo child3","variables":{},"lists":{},"broadcasts":{},"blocks":{"Ld;w(N?A?wgQwJts[*Bk":{"opcode":"event_whenbroadcastreceived","next":"62;F}[MD!}NC8FhQ.I7f","parent":null,"inputs":{},"fields":{"BROADCAST_OPTION":["navajo","broadcastMsgId-navajo"]},"shadow":false,"topLevel":true,"x":615,"y":147},"62;F}[MD!}NC8FhQ.I7f":{"opcode":"control_repeat","next":null,"parent":"Ld;w(N?A?wgQwJts[*Bk","inputs":{"TIMES":[1,[6,"22"]],"SUBSTACK":[2,"Ya9kmlG7_T`4@[UbrtbT"]},"fields":{},"shadow":false,"topLevel":false},"Ya9kmlG7_T`4@[UbrtbT":{"opcode":"looks_nextcostume","next":"TYR83e_lrI1tvBqH}s#8","parent":"62;F}[MD!}NC8FhQ.I7f","inputs":{},"fields":{},"shadow":false,"topLevel":false},"TYR83e_lrI1tvBqH}s#8":{"opcode":"control_wait","next":null,"parent":"Ya9kmlG7_T`4@[UbrtbT","inputs":{"DURATION":[1,[5,"0.5"]]},"fields":{},"shadow":false,"topLevel":false}},"comments":{},"currentCostume":0,"costumes":[{"assetId":"2c7f47643024e8df210b8311cbe7bbca","name":"center","bitmapResolution":1,"md5ext":"2c7f47643024e8df210b8311cbe7bbca.svg","dataFormat":"svg","rotationCenterX":37.5,"rotationCenterY":89.16666666666667},{"assetId":"eb71db9f55bab389a9690792ce37f4db","name":"left","bitmapResolution":1,"md5ext":"eb71db9f55bab389a9690792ce37f4db.svg","dataFormat":"svg","rotationCenterX":37.599999999999994,"rotationCenterY":87.1},{"assetId":"eb8c8a0f2390ebf66d45a241f6a17278","name":"center2","bitmapResolution":1,"md5ext":"eb8c8a0f2390ebf66d45a241f6a17278.svg","dataFormat":"svg","rotationCenterX":36.849999999999994,"rotationCenterY":87.55000000000001},{"assetId":"4227600146980e273a41c89a16ef0556","name":"right","bitmapResolution":1,"md5ext":"4227600146980e273a41c89a16ef0556.svg","dataFormat":"svg","rotationCenterX":37.44999999999999,"rotationCenterY":88.94999999999999}],"sounds":[{"assetId":"83a9787d4cb6f3b7632b4ddfebf74367","name":"pop","dataFormat":"wav","format":"","rate":48000,"sampleCount":1123,"md5ext":"83a9787d4cb6f3b7632b4ddfebf74367.wav"}],"volume":100,"layerOrder":7,"visible":true,"x":-96.99999999999999,"y":-60.000000000000014,"size":100,"direction":90,"draggable":false,"rotationStyle":"all around"},{"isStage":false,"name":"Mali child","variables":{},"lists":{},"broadcasts":{},"blocks":{"ScrI3V+!LzsusSo.bVWX":{"opcode":"event_whenflagclicked","next":"o7;%v}JMB^s`[nhYMX1;","parent":null,"inputs":{},"fields":{},"shadow":false,"topLevel":true,"x":679,"y":-195},"o7;%v}JMB^s`[nhYMX1;":{"opcode":"motion_gotoxy","next":null,"parent":"ScrI3V+!LzsusSo.bVWX","inputs":{"X":[1,[4,100]],"Y":[1,[4,-26]]},"fields":{},"shadow":false,"topLevel":false},"ju24DNGh1!eZRLqq42ed":{"opcode":"event_whenbroadcastreceived","next":"fFl}oYq/j]Uk6_r?q!9n","parent":null,"inputs":{},"fields":{"BROADCAST_OPTION":["Mali Djembe","TL?SB+/IyvN1M{jjF7`["]},"shadow":false,"topLevel":true,"x":688,"y":-4},"fFl}oYq/j]Uk6_r?q!9n":{"opcode":"control_repeat","next":null,"parent":"ju24DNGh1!eZRLqq42ed","inputs":{"TIMES":[1,[6,"22"]],"SUBSTACK":[3,"j7hIM*@zLiAZeWqz(:y#",null]},"fields":{},"shadow":false,"topLevel":false},"j7hIM*@zLiAZeWqz(:y#":{"opcode":"looks_nextcostume","next":"G:z0))F^]Yr@J}q(ph7[","parent":"fFl}oYq/j]Uk6_r?q!9n","inputs":{},"fields":{},"shadow":false,"topLevel":false},"G:z0))F^]Yr@J}q(ph7[":{"opcode":"control_wait","next":null,"parent":"j7hIM*@zLiAZeWqz(:y#","inputs":{"DURATION":[1,[5,"0.5"]]},"fields":{},"shadow":false,"topLevel":false}},"comments":{},"currentCostume":2,"costumes":[{"assetId":"7aed63bae8d366377e1b1ac7c534763c","name":"center","bitmapResolution":1,"md5ext":"7aed63bae8d366377e1b1ac7c534763c.svg","dataFormat":"svg","rotationCenterX":34,"rotationCenterY":84},{"assetId":"980d68ab932bfd08a77d6d1966d90539","name":"left","bitmapResolution":1,"md5ext":"980d68ab932bfd08a77d6d1966d90539.svg","dataFormat":"svg","rotationCenterX":59,"rotationCenterY":86},{"assetId":"f93976ee08897d366808878ac5b442b7","name":"center2","bitmapResolution":1,"md5ext":"f93976ee08897d366808878ac5b442b7.svg","dataFormat":"svg","rotationCenterX":37,"rotationCenterY":80},{"assetId":"de518bbf2bb8fbab0337e28ae0458c62","name":"right","bitmapResolution":1,"md5ext":"de518bbf2bb8fbab0337e28ae0458c62.svg","dataFormat":"svg","rotationCenterX":38,"rotationCenterY":86}],"sounds":[{"assetId":"83a9787d4cb6f3b7632b4ddfebf74367","name":"pop","dataFormat":"wav","format":"","rate":48000,"sampleCount":1123,"md5ext":"83a9787d4cb6f3b7632b4ddfebf74367.wav"}],"volume":100,"layerOrder":1,"visible":true,"x":100,"y":-26,"size":100,"direction":90,"draggable":false,"rotationStyle":"all around"},{"isStage":false,"name":"Navajo Flute2","variables":{},"lists":{},"broadcasts":{},"blocks":{"$XZ(mp}CL7*U6%2Ucr`|":{"opcode":"event_whenflagclicked","next":"~)^dCW.RNgKV3VirGW1N","parent":null,"inputs":{},"fields":{},"shadow":false,"topLevel":true,"x":712,"y":67},"~)^dCW.RNgKV3VirGW1N":{"opcode":"event_broadcast","next":"Pf7n=)Fa#eB~KUx(OJ[F","parent":"$XZ(mp}CL7*U6%2Ucr`|","inputs":{"BROADCAST_INPUT":[1,[11,"navajo","broadcastMsgId-navajo"]]},"fields":{},"shadow":false,"topLevel":false},"Pf7n=)Fa#eB~KUx(OJ[F":{"opcode":"sound_play","next":null,"parent":"~)^dCW.RNgKV3VirGW1N","inputs":{"SOUND_MENU":[1,"PEprv801o-24Maez0V%)"]},"fields":{},"shadow":false,"topLevel":false},"PEprv801o-24Maez0V%)":{"opcode":"sound_sounds_menu","next":null,"parent":"Pf7n=)Fa#eB~KUx(OJ[F","inputs":{},"fields":{"SOUND_MENU":["Navajo Flute",null]},"shadow":true,"topLevel":false}},"comments":{},"currentCostume":0,"costumes":[{"assetId":"e9e4203fecd6794d9a53876fbc33bd92","name":"nativeAmericanFlute","bitmapResolution":2,"md5ext":"e9e4203fecd6794d9a53876fbc33bd92.png","dataFormat":"png","rotationCenterX":192,"rotationCenterY":149}],"sounds":[{"assetId":"0f0f24fc2b4e03758aa90109b7e3e305","name":"Navajo Flute","dataFormat":"wav","format":"","rate":48000,"sampleCount":525792,"md5ext":"0f0f24fc2b4e03758aa90109b7e3e305.wav"}],"volume":100,"layerOrder":3,"visible":true,"x":20,"y":-160,"size":100,"direction":90,"draggable":false,"rotationStyle":"all around"}],"monitors":[{"id":"+Y:KzQ2YKvPQBK#]yay8-broadcast message-","mode":"default","opcode":"data_variable","params":{"VARIABLE":"broadcast message"},"spriteName":null,"value":"","x":5,"y":5,"visible":false,"sliderMin":0,"sliderMax":100,"isDiscrete":true},{"id":"+Y:KzQ2YKvPQBK#]yay8-add to band-","mode":"default","opcode":"data_variable","params":{"VARIABLE":"add to band"},"spriteName":null,"value":"","x":5,"y":32,"visible":false,"sliderMin":0,"sliderMax":100,"isDiscrete":true}],"extensions":[],"meta":{"semver":"3.0.0","vm":"0.2.0-prerelease.20190321151527","agent":"Mozilla/5.0 (Windows NT 10.0; Win64; x64) AppleWebKit/537.36 (KHTML, like Gecko) Chrome/68.0.3440.84 Safari/537.36"}}